<?xml version="1.0" encoding="Windows-1252"?>
<!DOCTYPE POWERMART SYSTEM "powrmart.dtd">
<POWERMART CREATION_DATE="11/21/2024 03:10:32" REPOSITORY_VERSION="187.96">
<REPOSITORY NAME="REP_DEV" VERSION="187" CODEPAGE="MS1252" DATABASETYPE="Microsoft SQL Server">
<FOLDER NAME="dev_practice" GROUP="" OWNER="Administrator" SHARED="NOTSHARED" DESCRIPTION="" PERMISSIONS="rwx---r--" UUID="e70468db-b04f-4cca-b67e-77e89d1606eb">
    <SOURCE BUSINESSNAME ="" DATABASETYPE ="Microsoft SQL Server" DBDNAME ="sqlexp" DESCRIPTION ="" NAME ="employees" OBJECTVERSION ="1" OWNERNAME ="dbo" VERSIONNUMBER ="1">
        <SOURCEFIELD BUSINESSNAME ="" DATATYPE ="int" DESCRIPTION ="" FIELDNUMBER ="1" FIELDPROPERTY ="0" FIELDTYPE ="ELEMITEM" HIDDEN ="NO" KEYTYPE ="PRIMARY KEY" LENGTH ="11" LEVEL ="0" NAME ="employee_id" NULLABLE ="NOTNULL" OCCURS ="0" OFFSET ="0" PHYSICALLENGTH ="10" PHYSICALOFFSET ="0" PICTURETEXT ="" PRECISION ="10" SCALE ="0" USAGE_FLAGS =""/>
        <SOURCEFIELD BUSINESSNAME ="" DATATYPE ="varchar" DESCRIPTION ="" FIELDNUMBER ="2" FIELDPROPERTY ="0" FIELDTYPE ="ELEMITEM" HIDDEN ="NO" KEYTYPE ="NOT A KEY" LENGTH ="0" LEVEL ="0" NAME ="first_name" NULLABLE ="NULL" OCCURS ="0" OFFSET ="11" PHYSICALLENGTH ="20" PHYSICALOFFSET ="10" PICTURETEXT ="" PRECISION ="20" SCALE ="0" USAGE_FLAGS =""/>
        <SOURCEFIELD BUSINESSNAME ="" DATATYPE ="varchar" DESCRIPTION ="" FIELDNUMBER ="3" FIELDPROPERTY ="0" FIELDTYPE ="ELEMITEM" HIDDEN ="NO" KEYTYPE ="NOT A KEY" LENGTH ="0" LEVEL ="0" NAME ="last_name" NULLABLE ="NOTNULL" OCCURS ="0" OFFSET ="11" PHYSICALLENGTH ="25" PHYSICALOFFSET ="30" PICTURETEXT ="" PRECISION ="25" SCALE ="0" USAGE_FLAGS =""/>
        <SOURCEFIELD BUSINESSNAME ="" DATATYPE ="varchar" DESCRIPTION ="" FIELDNUMBER ="4" FIELDPROPERTY ="0" FIELDTYPE ="ELEMITEM" HIDDEN ="NO" KEYTYPE ="NOT A KEY" LENGTH ="0" LEVEL ="0" NAME ="email" NULLABLE ="NOTNULL" OCCURS ="0" OFFSET ="11" PHYSICALLENGTH ="100" PHYSICALOFFSET ="55" PICTURETEXT ="" PRECISION ="100" SCALE ="0" USAGE_FLAGS =""/>
        <SOURCEFIELD BUSINESSNAME ="" DATATYPE ="varchar" DESCRIPTION ="" FIELDNUMBER ="5" FIELDPROPERTY ="0" FIELDTYPE ="ELEMITEM" HIDDEN ="NO" KEYTYPE ="NOT A KEY" LENGTH ="0" LEVEL ="0" NAME ="phone_number" NULLABLE ="NULL" OCCURS ="0" OFFSET ="11" PHYSICALLENGTH ="20" PHYSICALOFFSET ="155" PICTURETEXT ="" PRECISION ="20" SCALE ="0" USAGE_FLAGS =""/>
        <SOURCEFIELD BUSINESSNAME ="" DATATYPE ="nvarchar" DESCRIPTION ="" FIELDNUMBER ="6" FIELDPROPERTY ="0" FIELDTYPE ="ELEMITEM" HIDDEN ="NO" KEYTYPE ="NOT A KEY" LENGTH ="0" LEVEL ="0" NAME ="hire_date" NULLABLE ="NOTNULL" OCCURS ="0" OFFSET ="11" PHYSICALLENGTH ="10" PHYSICALOFFSET ="175" PICTURETEXT ="" PRECISION ="10" SCALE ="0" USAGE_FLAGS =""/>
        <SOURCEFIELD BUSINESSNAME ="" DATATYPE ="int" DESCRIPTION ="" FIELDNUMBER ="7" FIELDPROPERTY ="0" FIELDTYPE ="ELEMITEM" HIDDEN ="NO" KEYTYPE ="NOT A KEY" LENGTH ="11" LEVEL ="0" NAME ="job_id" NULLABLE ="NOTNULL" OCCURS ="0" OFFSET ="11" PHYSICALLENGTH ="10" PHYSICALOFFSET ="185" PICTURETEXT ="" PRECISION ="10" SCALE ="0" USAGE_FLAGS =""/>
        <SOURCEFIELD BUSINESSNAME ="" DATATYPE ="decimal" DESCRIPTION ="" FIELDNUMBER ="8" FIELDPROPERTY ="0" FIELDTYPE ="ELEMITEM" HIDDEN ="NO" KEYTYPE ="NOT A KEY" LENGTH ="10" LEVEL ="0" NAME ="salary" NULLABLE ="NOTNULL" OCCURS ="0" OFFSET ="22" PHYSICALLENGTH ="8" PHYSICALOFFSET ="195" PICTURETEXT ="" PRECISION ="8" SCALE ="2" USAGE_FLAGS =""/>
        <SOURCEFIELD BUSINESSNAME ="" DATATYPE ="int" DESCRIPTION ="" FIELDNUMBER ="9" FIELDPROPERTY ="0" FIELDTYPE ="ELEMITEM" HIDDEN ="NO" KEYTYPE ="FOREIGN KEY" LENGTH ="11" LEVEL ="0" NAME ="manager_id" NULLABLE ="NULL" OCCURS ="0" OFFSET ="32" PHYSICALLENGTH ="10" PHYSICALOFFSET ="203" PICTURETEXT ="" PRECISION ="10" REFERENCEDDBD ="sqlexp" REFERENCEDFIELD ="employee_id" REFERENCEDTABLE ="employees" SCALE ="0" USAGE_FLAGS =""/>
        <SOURCEFIELD BUSINESSNAME ="" DATATYPE ="int" DESCRIPTION ="" FIELDNUMBER ="10" FIELDPROPERTY ="0" FIELDTYPE ="ELEMITEM" HIDDEN ="NO" KEYTYPE ="NOT A KEY" LENGTH ="11" LEVEL ="0" NAME ="department_id" NULLABLE ="NULL" OCCURS ="0" OFFSET ="43" PHYSICALLENGTH ="10" PHYSICALOFFSET ="213" PICTURETEXT ="" PRECISION ="10" SCALE ="0" USAGE_FLAGS =""/>
    </SOURCE>
    <TARGET BUSINESSNAME ="" CONSTRAINT ="" DATABASETYPE ="Flat File" DESCRIPTION ="" NAME ="tgt_ff_sal_email_load" OBJECTVERSION ="1" TABLEOPTIONS ="" VERSIONNUMBER ="1">
        <FLATFILE CODEPAGE ="MS1252" CONSECDELIMITERSASONE ="NO" DELIMITED ="YES" DELIMITERS ="," ESCAPE_CHARACTER ="" KEEPESCAPECHAR ="NO" LINESEQUENTIAL ="NO" MULTIDELIMITERSASAND ="NO" NULLCHARTYPE ="ASCII" NULL_CHARACTER ="*" PADBYTES ="1" QUOTE_CHARACTER ="NONE" REPEATABLE ="NO" ROWDELIMITER ="0" SKIPROWS ="0" STRIPTRAILINGBLANKS ="NO"/>
        <TARGETFIELD BUSINESSNAME ="" DATATYPE ="int" DESCRIPTION ="" FIELDNUMBER ="1" KEYTYPE ="NOT A KEY" NAME ="manager_id" NULLABLE ="NULL" PICTURETEXT ="" PRECISION ="10" SCALE ="0"/>
        <TARGETFIELD BUSINESSNAME ="" DATATYPE ="string" DESCRIPTION ="" FIELDNUMBER ="2" KEYTYPE ="NOT A KEY" NAME ="manager_first_name" NULLABLE ="NULL" PICTURETEXT ="" PRECISION ="10" SCALE ="0"/>
        <TARGETFIELD BUSINESSNAME ="" DATATYPE ="string" DESCRIPTION ="" FIELDNUMBER ="3" KEYTYPE ="NOT A KEY" NAME ="manager_last_name" NULLABLE ="NULL" PICTURETEXT ="" PRECISION ="10" SCALE ="0"/>
        <TARGETFIELD BUSINESSNAME ="" DATATYPE ="string" DESCRIPTION ="" FIELDNUMBER ="4" KEYTYPE ="NOT A KEY" NAME ="manager_email" NULLABLE ="NULL" PICTURETEXT ="" PRECISION ="10" SCALE ="0"/>
        <TARGETFIELD BUSINESSNAME ="" DATATYPE ="string" DESCRIPTION ="" FIELDNUMBER ="5" KEYTYPE ="NOT A KEY" NAME ="email_domain" NULLABLE ="NULL" PICTURETEXT ="" PRECISION ="10" SCALE ="0"/>
        <TARGETFIELD BUSINESSNAME ="" DATATYPE ="double" DESCRIPTION ="" FIELDNUMBER ="6" KEYTYPE ="NOT A KEY" NAME ="max_salary" NULLABLE ="NULL" PICTURETEXT ="" PRECISION ="10" SCALE ="0"/>
        <TARGETFIELD BUSINESSNAME ="" DATATYPE ="double" DESCRIPTION ="" FIELDNUMBER ="7" KEYTYPE ="NOT A KEY" NAME ="min_salary" NULLABLE ="NULL" PICTURETEXT ="" PRECISION ="10" SCALE ="0"/>
        <TARGETFIELD BUSINESSNAME ="" DATATYPE ="double" DESCRIPTION ="" FIELDNUMBER ="8" KEYTYPE ="NOT A KEY" NAME ="avg_salary" NULLABLE ="NULL" PICTURETEXT ="" PRECISION ="10" SCALE ="0"/>
        <TARGETFIELD BUSINESSNAME ="" DATATYPE ="datetime" DESCRIPTION ="" FIELDNUMBER ="9" KEYTYPE ="NOT A KEY" NAME ="load_date" NULLABLE ="NULL" PICTURETEXT ="" PRECISION ="29" SCALE ="9"/>
        <TABLEATTRIBUTE NAME ="Datetime Format" VALUE ="A  19 mm/dd/yyyy hh24:mi:ss"/>
        <TABLEATTRIBUTE NAME ="Thousand Separator" VALUE ="None"/>
        <TABLEATTRIBUTE NAME ="Decimal Separator" VALUE ="."/>
        <TABLEATTRIBUTE NAME ="Line Endings" VALUE ="System default"/>
    </TARGET>
    <MAPPING DESCRIPTION ="" ISVALID ="YES" NAME ="m_sal_email_load" OBJECTVERSION ="1" VERSIONNUMBER ="1">
        <TRANSFORMATION DESCRIPTION ="" NAME ="SQ_employees" OBJECTVERSION ="1" REUSABLE ="NO" TYPE ="Source Qualifier" VERSIONNUMBER ="1">
            <TRANSFORMFIELD DATATYPE ="integer" DEFAULTVALUE ="" DESCRIPTION ="" NAME ="employee_id" PICTURETEXT ="" PORTTYPE ="INPUT/OUTPUT" PRECISION ="10" SCALE ="0"/>
            <TRANSFORMFIELD DATATYPE ="string" DEFAULTVALUE ="" DESCRIPTION ="" NAME ="first_name" PICTURETEXT ="" PORTTYPE ="INPUT/OUTPUT" PRECISION ="20" SCALE ="0"/>
            <TRANSFORMFIELD DATATYPE ="string" DEFAULTVALUE ="" DESCRIPTION ="" NAME ="last_name" PICTURETEXT ="" PORTTYPE ="INPUT/OUTPUT" PRECISION ="25" SCALE ="0"/>
            <TRANSFORMFIELD DATATYPE ="string" DEFAULTVALUE ="" DESCRIPTION ="" NAME ="email" PICTURETEXT ="" PORTTYPE ="INPUT/OUTPUT" PRECISION ="100" SCALE ="0"/>
            <TRANSFORMFIELD DATATYPE ="string" DEFAULTVALUE ="" DESCRIPTION ="" NAME ="phone_number" PICTURETEXT ="" PORTTYPE ="INPUT/OUTPUT" PRECISION ="20" SCALE ="0"/>
            <TRANSFORMFIELD DATATYPE ="nstring" DEFAULTVALUE ="" DESCRIPTION ="" NAME ="hire_date" PICTURETEXT ="" PORTTYPE ="INPUT/OUTPUT" PRECISION ="10" SCALE ="0"/>
            <TRANSFORMFIELD DATATYPE ="integer" DEFAULTVALUE ="" DESCRIPTION ="" NAME ="job_id" PICTURETEXT ="" PORTTYPE ="INPUT/OUTPUT" PRECISION ="10" SCALE ="0"/>
            <TRANSFORMFIELD DATATYPE ="decimal" DEFAULTVALUE ="" DESCRIPTION ="" NAME ="salary" PICTURETEXT ="" PORTTYPE ="INPUT/OUTPUT" PRECISION ="8" SCALE ="2"/>
            <TRANSFORMFIELD DATATYPE ="integer" DEFAULTVALUE ="" DESCRIPTION ="" NAME ="manager_id" PICTURETEXT ="" PORTTYPE ="INPUT/OUTPUT" PRECISION ="10" SCALE ="0"/>
            <TRANSFORMFIELD DATATYPE ="integer" DEFAULTVALUE ="" DESCRIPTION ="" NAME ="department_id" PICTURETEXT ="" PORTTYPE ="INPUT/OUTPUT" PRECISION ="10" SCALE ="0"/>
            <TABLEATTRIBUTE NAME ="Sql Query" VALUE =""/>
            <TABLEATTRIBUTE NAME ="User Defined Join" VALUE =""/>
            <TABLEATTRIBUTE NAME ="Source Filter" VALUE =""/>
            <TABLEATTRIBUTE NAME ="Number Of Sorted Ports" VALUE ="0"/>
            <TABLEATTRIBUTE NAME ="Tracing Level" VALUE ="Normal"/>
            <TABLEATTRIBUTE NAME ="Select Distinct" VALUE ="NO"/>
            <TABLEATTRIBUTE NAME ="Is Partitionable" VALUE ="NO"/>
            <TABLEATTRIBUTE NAME ="Pre SQL" VALUE =""/>
            <TABLEATTRIBUTE NAME ="Post SQL" VALUE =""/>
            <TABLEATTRIBUTE NAME ="Output is deterministic" VALUE ="NO"/>
            <TABLEATTRIBUTE NAME ="Output is repeatable" VALUE ="Never"/>
        </TRANSFORMATION>
        <TRANSFORMATION DESCRIPTION ="" NAME ="aggr_manager_id" OBJECTVERSION ="1" REUSABLE ="NO" TYPE ="Aggregator" VERSIONNUMBER ="1">
            <TRANSFORMFIELD DATATYPE ="integer" DEFAULTVALUE ="" DESCRIPTION ="" EXPRESSION ="manager_id" EXPRESSIONTYPE ="GROUPBY" NAME ="manager_id" PICTURETEXT ="" PORTTYPE ="INPUT/OUTPUT" PRECISION ="10" SCALE ="0"/>
            <TRANSFORMFIELD DATATYPE ="decimal" DEFAULTVALUE ="" DESCRIPTION ="" EXPRESSION ="salary" EXPRESSIONTYPE ="GENERAL" NAME ="salary" PICTURETEXT ="" PORTTYPE ="INPUT/OUTPUT" PRECISION ="8" SCALE ="2"/>
            <TRANSFORMFIELD DATATYPE ="decimal" DEFAULTVALUE ="ERROR(&apos;transformation error&apos;)" DESCRIPTION ="" EXPRESSION ="MAX(salary)" EXPRESSIONTYPE ="GENERAL" NAME ="max_salary" PICTURETEXT ="" PORTTYPE ="OUTPUT" PRECISION ="10" SCALE ="0"/>
            <TRANSFORMFIELD DATATYPE ="decimal" DEFAULTVALUE ="ERROR(&apos;transformation error&apos;)" DESCRIPTION ="" EXPRESSION ="MIN(salary)" EXPRESSIONTYPE ="GENERAL" NAME ="min_salary" PICTURETEXT ="" PORTTYPE ="OUTPUT" PRECISION ="10" SCALE ="0"/>
            <TRANSFORMFIELD DATATYPE ="decimal" DEFAULTVALUE ="ERROR(&apos;transformation error&apos;)" DESCRIPTION ="" EXPRESSION ="AVG(salary)" EXPRESSIONTYPE ="GENERAL" NAME ="avg_salary" PICTURETEXT ="" PORTTYPE ="OUTPUT" PRECISION ="10" SCALE ="0"/>
            <TABLEATTRIBUTE NAME ="Cache Directory" VALUE ="$PMCacheDir"/>
            <TABLEATTRIBUTE NAME ="Tracing Level" VALUE ="Normal"/>
            <TABLEATTRIBUTE NAME ="Sorted Input" VALUE ="NO"/>
            <TABLEATTRIBUTE NAME ="Aggregator Data Cache Size" VALUE ="Auto"/>
            <TABLEATTRIBUTE NAME ="Aggregator Index Cache Size" VALUE ="Auto"/>
            <TABLEATTRIBUTE NAME ="Transformation Scope" VALUE ="All Input"/>
        </TRANSFORMATION>
        <TRANSFORMATION DESCRIPTION ="" NAME ="SQ_employees1" OBJECTVERSION ="1" REUSABLE ="NO" TYPE ="Source Qualifier" VERSIONNUMBER ="1">
            <TRANSFORMFIELD DATATYPE ="integer" DEFAULTVALUE ="" DESCRIPTION ="" NAME ="employee_id" PICTURETEXT ="" PORTTYPE ="INPUT/OUTPUT" PRECISION ="10" SCALE ="0"/>
            <TRANSFORMFIELD DATATYPE ="string" DEFAULTVALUE ="" DESCRIPTION ="" NAME ="first_name" PICTURETEXT ="" PORTTYPE ="INPUT/OUTPUT" PRECISION ="20" SCALE ="0"/>
            <TRANSFORMFIELD DATATYPE ="string" DEFAULTVALUE ="" DESCRIPTION ="" NAME ="last_name" PICTURETEXT ="" PORTTYPE ="INPUT/OUTPUT" PRECISION ="25" SCALE ="0"/>
            <TRANSFORMFIELD DATATYPE ="string" DEFAULTVALUE ="" DESCRIPTION ="" NAME ="email" PICTURETEXT ="" PORTTYPE ="INPUT/OUTPUT" PRECISION ="100" SCALE ="0"/>
            <TRANSFORMFIELD DATATYPE ="string" DEFAULTVALUE ="" DESCRIPTION ="" NAME ="phone_number" PICTURETEXT ="" PORTTYPE ="INPUT/OUTPUT" PRECISION ="20" SCALE ="0"/>
            <TRANSFORMFIELD DATATYPE ="nstring" DEFAULTVALUE ="" DESCRIPTION ="" NAME ="hire_date" PICTURETEXT ="" PORTTYPE ="INPUT/OUTPUT" PRECISION ="10" SCALE ="0"/>
            <TRANSFORMFIELD DATATYPE ="integer" DEFAULTVALUE ="" DESCRIPTION ="" NAME ="job_id" PICTURETEXT ="" PORTTYPE ="INPUT/OUTPUT" PRECISION ="10" SCALE ="0"/>
            <TRANSFORMFIELD DATATYPE ="decimal" DEFAULTVALUE ="" DESCRIPTION ="" NAME ="salary" PICTURETEXT ="" PORTTYPE ="INPUT/OUTPUT" PRECISION ="8" SCALE ="2"/>
            <TRANSFORMFIELD DATATYPE ="integer" DEFAULTVALUE ="" DESCRIPTION ="" NAME ="manager_id" PICTURETEXT ="" PORTTYPE ="INPUT/OUTPUT" PRECISION ="10" SCALE ="0"/>
            <TRANSFORMFIELD DATATYPE ="integer" DEFAULTVALUE ="" DESCRIPTION ="" NAME ="department_id" PICTURETEXT ="" PORTTYPE ="INPUT/OUTPUT" PRECISION ="10" SCALE ="0"/>
            <TABLEATTRIBUTE NAME ="Sql Query" VALUE =""/>
            <TABLEATTRIBUTE NAME ="User Defined Join" VALUE =""/>
            <TABLEATTRIBUTE NAME ="Source Filter" VALUE =""/>
            <TABLEATTRIBUTE NAME ="Number Of Sorted Ports" VALUE ="0"/>
            <TABLEATTRIBUTE NAME ="Tracing Level" VALUE ="Normal"/>
            <TABLEATTRIBUTE NAME ="Select Distinct" VALUE ="NO"/>
            <TABLEATTRIBUTE NAME ="Is Partitionable" VALUE ="NO"/>
            <TABLEATTRIBUTE NAME ="Pre SQL" VALUE =""/>
            <TABLEATTRIBUTE NAME ="Post SQL" VALUE =""/>
            <TABLEATTRIBUTE NAME ="Output is deterministic" VALUE ="NO"/>
            <TABLEATTRIBUTE NAME ="Output is repeatable" VALUE ="Never"/>
        </TRANSFORMATION>
        <TRANSFORMATION DESCRIPTION ="" NAME ="jn_manager_agg" OBJECTVERSION ="1" REUSABLE ="NO" TYPE ="Joiner" VERSIONNUMBER ="1">
            <TRANSFORMFIELD DATATYPE ="integer" DEFAULTVALUE ="" DESCRIPTION ="" NAME ="manager_id" PICTURETEXT ="" PORTTYPE ="INPUT/OUTPUT" PRECISION ="10" SCALE ="0"/>
            <TRANSFORMFIELD DATATYPE ="integer" DEFAULTVALUE ="" DESCRIPTION ="" NAME ="employee_id" PICTURETEXT ="" PORTTYPE ="INPUT/OUTPUT/MASTER" PRECISION ="10" SCALE ="0"/>
            <TRANSFORMFIELD DATATYPE ="string" DEFAULTVALUE ="" DESCRIPTION ="" NAME ="manager_first_name" PICTURETEXT ="" PORTTYPE ="INPUT/OUTPUT/MASTER" PRECISION ="20" SCALE ="0"/>
            <TRANSFORMFIELD DATATYPE ="string" DEFAULTVALUE ="" DESCRIPTION ="" NAME ="manager_last_name" PICTURETEXT ="" PORTTYPE ="INPUT/OUTPUT/MASTER" PRECISION ="25" SCALE ="0"/>
            <TRANSFORMFIELD DATATYPE ="string" DEFAULTVALUE ="" DESCRIPTION ="" NAME ="manager_email" PICTURETEXT ="" PORTTYPE ="INPUT/OUTPUT/MASTER" PRECISION ="100" SCALE ="0"/>
            <TRANSFORMFIELD DATATYPE ="decimal" DEFAULTVALUE ="" DESCRIPTION ="" NAME ="max_salary" PICTURETEXT ="" PORTTYPE ="INPUT/OUTPUT" PRECISION ="10" SCALE ="0"/>
            <TRANSFORMFIELD DATATYPE ="decimal" DEFAULTVALUE ="" DESCRIPTION ="" NAME ="min_salary" PICTURETEXT ="" PORTTYPE ="INPUT/OUTPUT" PRECISION ="10" SCALE ="0"/>
            <TRANSFORMFIELD DATATYPE ="decimal" DEFAULTVALUE ="" DESCRIPTION ="" NAME ="avg_salary" PICTURETEXT ="" PORTTYPE ="INPUT/OUTPUT" PRECISION ="10" SCALE ="0"/>
            <TABLEATTRIBUTE NAME ="Case Sensitive String Comparison" VALUE ="YES"/>
            <TABLEATTRIBUTE NAME ="Cache Directory" VALUE ="$PMCacheDir"/>
            <TABLEATTRIBUTE NAME ="Join Condition" VALUE ="employee_id = manager_id"/>
            <TABLEATTRIBUTE NAME ="Join Type" VALUE ="Normal Join"/>
            <TABLEATTRIBUTE NAME ="Null ordering in master" VALUE ="Null Is Highest Value"/>
            <TABLEATTRIBUTE NAME ="Null ordering in detail" VALUE ="Null Is Highest Value"/>
            <TABLEATTRIBUTE NAME ="Tracing Level" VALUE ="Normal"/>
            <TABLEATTRIBUTE NAME ="Joiner Data Cache Size" VALUE ="Auto"/>
            <TABLEATTRIBUTE NAME ="Joiner Index Cache Size" VALUE ="Auto"/>
            <TABLEATTRIBUTE NAME ="Sorted Input" VALUE ="YES"/>
            <TABLEATTRIBUTE NAME ="Master Sort Order" VALUE ="Auto"/>
            <TABLEATTRIBUTE NAME ="Transformation Scope" VALUE ="All Input"/>
        </TRANSFORMATION>
        <TRANSFORMATION DESCRIPTION ="" NAME ="exp_email_domain" OBJECTVERSION ="1" REUSABLE ="NO" TYPE ="Expression" VERSIONNUMBER ="1">
            <TRANSFORMFIELD DATATYPE ="string" DEFAULTVALUE ="" DESCRIPTION ="" EXPRESSION ="manager_email" EXPRESSIONTYPE ="GENERAL" NAME ="manager_email" PICTURETEXT ="" PORTTYPE ="INPUT/OUTPUT" PRECISION ="100" SCALE ="0"/>
            <TRANSFORMFIELD DATATYPE ="string" DEFAULTVALUE ="ERROR(&apos;transformation error&apos;)" DESCRIPTION ="" EXPRESSION ="SUBSTR(manager_email, INSTR(manager_email, &apos;@&apos;) + 1)&#xD;&#xA;" EXPRESSIONTYPE ="GENERAL" NAME ="email_domain" PICTURETEXT ="" PORTTYPE ="OUTPUT" PRECISION ="50" SCALE ="0"/>
            <TRANSFORMFIELD DATATYPE ="string" DEFAULTVALUE ="" DESCRIPTION ="" EXPRESSION ="manager_first_name" EXPRESSIONTYPE ="GENERAL" NAME ="manager_first_name" PICTURETEXT ="" PORTTYPE ="INPUT/OUTPUT" PRECISION ="20" SCALE ="0"/>
            <TRANSFORMFIELD DATATYPE ="string" DEFAULTVALUE ="" DESCRIPTION ="" EXPRESSION ="manager_last_name" EXPRESSIONTYPE ="GENERAL" NAME ="manager_last_name" PICTURETEXT ="" PORTTYPE ="INPUT/OUTPUT" PRECISION ="25" SCALE ="0"/>
            <TRANSFORMFIELD DATATYPE ="decimal" DEFAULTVALUE ="" DESCRIPTION ="" EXPRESSION ="max_salary" EXPRESSIONTYPE ="GENERAL" NAME ="max_salary" PICTURETEXT ="" PORTTYPE ="INPUT/OUTPUT" PRECISION ="10" SCALE ="0"/>
            <TRANSFORMFIELD DATATYPE ="decimal" DEFAULTVALUE ="" DESCRIPTION ="" EXPRESSION ="min_salary" EXPRESSIONTYPE ="GENERAL" NAME ="min_salary" PICTURETEXT ="" PORTTYPE ="INPUT/OUTPUT" PRECISION ="10" SCALE ="0"/>
            <TRANSFORMFIELD DATATYPE ="decimal" DEFAULTVALUE ="" DESCRIPTION ="" EXPRESSION ="avg_salary" EXPRESSIONTYPE ="GENERAL" NAME ="avg_salary" PICTURETEXT ="" PORTTYPE ="INPUT/OUTPUT" PRECISION ="10" SCALE ="0"/>
            <TRANSFORMFIELD DATATYPE ="date/time" DEFAULTVALUE ="ERROR(&apos;transformation error&apos;)" DESCRIPTION ="" EXPRESSION ="SYSDATE&#xD;&#xA;" EXPRESSIONTYPE ="GENERAL" NAME ="load_date" PICTURETEXT ="" PORTTYPE ="OUTPUT" PRECISION ="29" SCALE ="9"/>
            <TRANSFORMFIELD DATATYPE ="integer" DEFAULTVALUE ="" DESCRIPTION ="" EXPRESSION ="manager_id" EXPRESSIONTYPE ="GENERAL" NAME ="manager_id" PICTURETEXT ="" PORTTYPE ="INPUT/OUTPUT" PRECISION ="10" SCALE ="0"/>
            <TABLEATTRIBUTE NAME ="Tracing Level" VALUE ="Normal"/>
        </TRANSFORMATION>
        <INSTANCE DBDNAME ="sqlexp" DESCRIPTION ="" NAME ="employees" TRANSFORMATION_NAME ="employees" TRANSFORMATION_TYPE ="Source Definition" TYPE ="SOURCE"/>
        <INSTANCE DESCRIPTION ="" NAME ="SQ_employees" REUSABLE ="NO" TRANSFORMATION_NAME ="SQ_employees" TRANSFORMATION_TYPE ="Source Qualifier" TYPE ="TRANSFORMATION">
            <ASSOCIATED_SOURCE_INSTANCE NAME ="employees"/>
        </INSTANCE>
        <INSTANCE DESCRIPTION ="" NAME ="aggr_manager_id" REUSABLE ="NO" TRANSFORMATION_NAME ="aggr_manager_id" TRANSFORMATION_TYPE ="Aggregator" TYPE ="TRANSFORMATION"/>
        <INSTANCE DBDNAME ="sqlexp" DESCRIPTION ="" NAME ="employees1" TRANSFORMATION_NAME ="employees" TRANSFORMATION_TYPE ="Source Definition" TYPE ="SOURCE"/>
        <INSTANCE DESCRIPTION ="" NAME ="SQ_employees1" REUSABLE ="NO" TRANSFORMATION_NAME ="SQ_employees1" TRANSFORMATION_TYPE ="Source Qualifier" TYPE ="TRANSFORMATION">
            <ASSOCIATED_SOURCE_INSTANCE NAME ="employees1"/>
        </INSTANCE>
        <INSTANCE DESCRIPTION ="" NAME ="jn_manager_agg" REUSABLE ="NO" TRANSFORMATION_NAME ="jn_manager_agg" TRANSFORMATION_TYPE ="Joiner" TYPE ="TRANSFORMATION"/>
        <INSTANCE DESCRIPTION ="" NAME ="exp_email_domain" REUSABLE ="NO" TRANSFORMATION_NAME ="exp_email_domain" TRANSFORMATION_TYPE ="Expression" TYPE ="TRANSFORMATION"/>
        <INSTANCE DESCRIPTION ="" NAME ="tgt_ff_sal_email_load" TRANSFORMATION_NAME ="tgt_ff_sal_email_load" TRANSFORMATION_TYPE ="Target Definition" TYPE ="TARGET"/>
        <CONNECTOR FROMFIELD ="employee_id" FROMINSTANCE ="employees" FROMINSTANCETYPE ="Source Definition" TOFIELD ="employee_id" TOINSTANCE ="SQ_employees" TOINSTANCETYPE ="Source Qualifier"/>
        <CONNECTOR FROMFIELD ="first_name" FROMINSTANCE ="employees" FROMINSTANCETYPE ="Source Definition" TOFIELD ="first_name" TOINSTANCE ="SQ_employees" TOINSTANCETYPE ="Source Qualifier"/>
        <CONNECTOR FROMFIELD ="last_name" FROMINSTANCE ="employees" FROMINSTANCETYPE ="Source Definition" TOFIELD ="last_name" TOINSTANCE ="SQ_employees" TOINSTANCETYPE ="Source Qualifier"/>
        <CONNECTOR FROMFIELD ="email" FROMINSTANCE ="employees" FROMINSTANCETYPE ="Source Definition" TOFIELD ="email" TOINSTANCE ="SQ_employees" TOINSTANCETYPE ="Source Qualifier"/>
        <CONNECTOR FROMFIELD ="phone_number" FROMINSTANCE ="employees" FROMINSTANCETYPE ="Source Definition" TOFIELD ="phone_number" TOINSTANCE ="SQ_employees" TOINSTANCETYPE ="Source Qualifier"/>
        <CONNECTOR FROMFIELD ="hire_date" FROMINSTANCE ="employees" FROMINSTANCETYPE ="Source Definition" TOFIELD ="hire_date" TOINSTANCE ="SQ_employees" TOINSTANCETYPE ="Source Qualifier"/>
        <CONNECTOR FROMFIELD ="job_id" FROMINSTANCE ="employees" FROMINSTANCETYPE ="Source Definition" TOFIELD ="job_id" TOINSTANCE ="SQ_employees" TOINSTANCETYPE ="Source Qualifier"/>
        <CONNECTOR FROMFIELD ="salary" FROMINSTANCE ="employees" FROMINSTANCETYPE ="Source Definition" TOFIELD ="salary" TOINSTANCE ="SQ_employees" TOINSTANCETYPE ="Source Qualifier"/>
        <CONNECTOR FROMFIELD ="manager_id" FROMINSTANCE ="employees" FROMINSTANCETYPE ="Source Definition" TOFIELD ="manager_id" TOINSTANCE ="SQ_employees" TOINSTANCETYPE ="Source Qualifier"/>
        <CONNECTOR FROMFIELD ="department_id" FROMINSTANCE ="employees" FROMINSTANCETYPE ="Source Definition" TOFIELD ="department_id" TOINSTANCE ="SQ_employees" TOINSTANCETYPE ="Source Qualifier"/>
        <CONNECTOR FROMFIELD ="manager_id" FROMINSTANCE ="SQ_employees" FROMINSTANCETYPE ="Source Qualifier" TOFIELD ="manager_id" TOINSTANCE ="aggr_manager_id" TOINSTANCETYPE ="Aggregator"/>
        <CONNECTOR FROMFIELD ="salary" FROMINSTANCE ="SQ_employees" FROMINSTANCETYPE ="Source Qualifier" TOFIELD ="salary" TOINSTANCE ="aggr_manager_id" TOINSTANCETYPE ="Aggregator"/>
        <CONNECTOR FROMFIELD ="manager_id" FROMINSTANCE ="aggr_manager_id" FROMINSTANCETYPE ="Aggregator" TOFIELD ="manager_id" TOINSTANCE ="jn_manager_agg" TOINSTANCETYPE ="Joiner"/>
        <CONNECTOR FROMFIELD ="max_salary" FROMINSTANCE ="aggr_manager_id" FROMINSTANCETYPE ="Aggregator" TOFIELD ="max_salary" TOINSTANCE ="jn_manager_agg" TOINSTANCETYPE ="Joiner"/>
        <CONNECTOR FROMFIELD ="min_salary" FROMINSTANCE ="aggr_manager_id" FROMINSTANCETYPE ="Aggregator" TOFIELD ="min_salary" TOINSTANCE ="jn_manager_agg" TOINSTANCETYPE ="Joiner"/>
        <CONNECTOR FROMFIELD ="avg_salary" FROMINSTANCE ="aggr_manager_id" FROMINSTANCETYPE ="Aggregator" TOFIELD ="avg_salary" TOINSTANCE ="jn_manager_agg" TOINSTANCETYPE ="Joiner"/>
        <CONNECTOR FROMFIELD ="employee_id" FROMINSTANCE ="employees1" FROMINSTANCETYPE ="Source Definition" TOFIELD ="employee_id" TOINSTANCE ="SQ_employees1" TOINSTANCETYPE ="Source Qualifier"/>
        <CONNECTOR FROMFIELD ="first_name" FROMINSTANCE ="employees1" FROMINSTANCETYPE ="Source Definition" TOFIELD ="first_name" TOINSTANCE ="SQ_employees1" TOINSTANCETYPE ="Source Qualifier"/>
        <CONNECTOR FROMFIELD ="last_name" FROMINSTANCE ="employees1" FROMINSTANCETYPE ="Source Definition" TOFIELD ="last_name" TOINSTANCE ="SQ_employees1" TOINSTANCETYPE ="Source Qualifier"/>
        <CONNECTOR FROMFIELD ="email" FROMINSTANCE ="employees1" FROMINSTANCETYPE ="Source Definition" TOFIELD ="email" TOINSTANCE ="SQ_employees1" TOINSTANCETYPE ="Source Qualifier"/>
        <CONNECTOR FROMFIELD ="phone_number" FROMINSTANCE ="employees1" FROMINSTANCETYPE ="Source Definition" TOFIELD ="phone_number" TOINSTANCE ="SQ_employees1" TOINSTANCETYPE ="Source Qualifier"/>
        <CONNECTOR FROMFIELD ="hire_date" FROMINSTANCE ="employees1" FROMINSTANCETYPE ="Source Definition" TOFIELD ="hire_date" TOINSTANCE ="SQ_employees1" TOINSTANCETYPE ="Source Qualifier"/>
        <CONNECTOR FROMFIELD ="job_id" FROMINSTANCE ="employees1" FROMINSTANCETYPE ="Source Definition" TOFIELD ="job_id" TOINSTANCE ="SQ_employees1" TOINSTANCETYPE ="Source Qualifier"/>
        <CONNECTOR FROMFIELD ="salary" FROMINSTANCE ="employees1" FROMINSTANCETYPE ="Source Definition" TOFIELD ="salary" TOINSTANCE ="SQ_employees1" TOINSTANCETYPE ="Source Qualifier"/>
        <CONNECTOR FROMFIELD ="manager_id" FROMINSTANCE ="employees1" FROMINSTANCETYPE ="Source Definition" TOFIELD ="manager_id" TOINSTANCE ="SQ_employees1" TOINSTANCETYPE ="Source Qualifier"/>
        <CONNECTOR FROMFIELD ="department_id" FROMINSTANCE ="employees1" FROMINSTANCETYPE ="Source Definition" TOFIELD ="department_id" TOINSTANCE ="SQ_employees1" TOINSTANCETYPE ="Source Qualifier"/>
        <CONNECTOR FROMFIELD ="employee_id" FROMINSTANCE ="SQ_employees1" FROMINSTANCETYPE ="Source Qualifier" TOFIELD ="employee_id" TOINSTANCE ="jn_manager_agg" TOINSTANCETYPE ="Joiner"/>
        <CONNECTOR FROMFIELD ="first_name" FROMINSTANCE ="SQ_employees1" FROMINSTANCETYPE ="Source Qualifier" TOFIELD ="manager_first_name" TOINSTANCE ="jn_manager_agg" TOINSTANCETYPE ="Joiner"/>
        <CONNECTOR FROMFIELD ="last_name" FROMINSTANCE ="SQ_employees1" FROMINSTANCETYPE ="Source Qualifier" TOFIELD ="manager_last_name" TOINSTANCE ="jn_manager_agg" TOINSTANCETYPE ="Joiner"/>
        <CONNECTOR FROMFIELD ="email" FROMINSTANCE ="SQ_employees1" FROMINSTANCETYPE ="Source Qualifier" TOFIELD ="manager_email" TOINSTANCE ="jn_manager_agg" TOINSTANCETYPE ="Joiner"/>
        <CONNECTOR FROMFIELD ="manager_email" FROMINSTANCE ="jn_manager_agg" FROMINSTANCETYPE ="Joiner" TOFIELD ="manager_email" TOINSTANCE ="exp_email_domain" TOINSTANCETYPE ="Expression"/>
        <CONNECTOR FROMFIELD ="manager_first_name" FROMINSTANCE ="jn_manager_agg" FROMINSTANCETYPE ="Joiner" TOFIELD ="manager_first_name" TOINSTANCE ="exp_email_domain" TOINSTANCETYPE ="Expression"/>
        <CONNECTOR FROMFIELD ="manager_last_name" FROMINSTANCE ="jn_manager_agg" FROMINSTANCETYPE ="Joiner" TOFIELD ="manager_last_name" TOINSTANCE ="exp_email_domain" TOINSTANCETYPE ="Expression"/>
        <CONNECTOR FROMFIELD ="max_salary" FROMINSTANCE ="jn_manager_agg" FROMINSTANCETYPE ="Joiner" TOFIELD ="max_salary" TOINSTANCE ="exp_email_domain" TOINSTANCETYPE ="Expression"/>
        <CONNECTOR FROMFIELD ="min_salary" FROMINSTANCE ="jn_manager_agg" FROMINSTANCETYPE ="Joiner" TOFIELD ="min_salary" TOINSTANCE ="exp_email_domain" TOINSTANCETYPE ="Expression"/>
        <CONNECTOR FROMFIELD ="avg_salary" FROMINSTANCE ="jn_manager_agg" FROMINSTANCETYPE ="Joiner" TOFIELD ="avg_salary" TOINSTANCE ="exp_email_domain" TOINSTANCETYPE ="Expression"/>
        <CONNECTOR FROMFIELD ="manager_id" FROMINSTANCE ="jn_manager_agg" FROMINSTANCETYPE ="Joiner" TOFIELD ="manager_id" TOINSTANCE ="exp_email_domain" TOINSTANCETYPE ="Expression"/>
        <CONNECTOR FROMFIELD ="manager_id" FROMINSTANCE ="exp_email_domain" FROMINSTANCETYPE ="Expression" TOFIELD ="manager_id" TOINSTANCE ="tgt_ff_sal_email_load" TOINSTANCETYPE ="Target Definition"/>
        <CONNECTOR FROMFIELD ="manager_first_name" FROMINSTANCE ="exp_email_domain" FROMINSTANCETYPE ="Expression" TOFIELD ="manager_first_name" TOINSTANCE ="tgt_ff_sal_email_load" TOINSTANCETYPE ="Target Definition"/>
        <CONNECTOR FROMFIELD ="manager_last_name" FROMINSTANCE ="exp_email_domain" FROMINSTANCETYPE ="Expression" TOFIELD ="manager_last_name" TOINSTANCE ="tgt_ff_sal_email_load" TOINSTANCETYPE ="Target Definition"/>
        <CONNECTOR FROMFIELD ="manager_email" FROMINSTANCE ="exp_email_domain" FROMINSTANCETYPE ="Expression" TOFIELD ="manager_email" TOINSTANCE ="tgt_ff_sal_email_load" TOINSTANCETYPE ="Target Definition"/>
        <CONNECTOR FROMFIELD ="email_domain" FROMINSTANCE ="exp_email_domain" FROMINSTANCETYPE ="Expression" TOFIELD ="email_domain" TOINSTANCE ="tgt_ff_sal_email_load" TOINSTANCETYPE ="Target Definition"/>
        <CONNECTOR FROMFIELD ="max_salary" FROMINSTANCE ="exp_email_domain" FROMINSTANCETYPE ="Expression" TOFIELD ="max_salary" TOINSTANCE ="tgt_ff_sal_email_load" TOINSTANCETYPE ="Target Definition"/>
        <CONNECTOR FROMFIELD ="min_salary" FROMINSTANCE ="exp_email_domain" FROMINSTANCETYPE ="Expression" TOFIELD ="min_salary" TOINSTANCE ="tgt_ff_sal_email_load" TOINSTANCETYPE ="Target Definition"/>
        <CONNECTOR FROMFIELD ="avg_salary" FROMINSTANCE ="exp_email_domain" FROMINSTANCETYPE ="Expression" TOFIELD ="avg_salary" TOINSTANCE ="tgt_ff_sal_email_load" TOINSTANCETYPE ="Target Definition"/>
        <CONNECTOR FROMFIELD ="load_date" FROMINSTANCE ="exp_email_domain" FROMINSTANCETYPE ="Expression" TOFIELD ="load_date" TOINSTANCE ="tgt_ff_sal_email_load" TOINSTANCETYPE ="Target Definition"/>
        <TARGETLOADORDER ORDER ="1" TARGETINSTANCE ="tgt_ff_sal_email_load"/>
    </MAPPING>
</FOLDER>
</REPOSITORY>
</POWERMART>